LICENSE
MANIFEST.in
README
dynamic-dynamodb
setup.py
dynamic_dynamodb/__init__.py
dynamic_dynamodb/calculators.py
dynamic_dynamodb/config_handler.py
dynamic_dynamodb/daemon.py
dynamic_dynamodb/dynamic-dynamodb.conf
dynamic_dynamodb/log_handler.py
dynamic_dynamodb/test_calculators.py
dynamic_dynamodb/test_scaling_metrics.py
dynamic_dynamodb.egg-info/PKG-INFO
dynamic_dynamodb.egg-info/SOURCES.txt
dynamic_dynamodb.egg-info/dependency_links.txt
dynamic_dynamodb.egg-info/not-zip-safe
dynamic_dynamodb.egg-info/requires.txt
dynamic_dynamodb.egg-info/top_level.txt
dynamic_dynamodb/aws/__init__.py
dynamic_dynamodb/aws/cloudwatch.py
dynamic_dynamodb/aws/dynamodb.py
dynamic_dynamodb/aws/sns.py
dynamic_dynamodb/config/__init__.py
dynamic_dynamodb/config/command_line_parser.py
dynamic_dynamodb/config/config_file_parser.py
dynamic_dynamodb/core/__init__.py
dynamic_dynamodb/core/circuit_breaker.py
dynamic_dynamodb/core/gsi.py
dynamic_dynamodb/core/table.py
dynamic_dynamodb/statistics/__init__.py
dynamic_dynamodb/statistics/gsi.py
dynamic_dynamodb/statistics/table.py