Metadata-Version: 1.1
Name: dynamic-dynamodb
Version: 2.5.0
Summary: Automatic provisioning for AWS DynamoDB tables
Home-page: http://sebdah.github.com/dynamic-dynamodb/
Author: Sebastian Dahlgren
Author-email: sebastian.dahlgren@gmail.com
License: Apache License, Version 2.0
Keywords: dynamodb aws provisioning amazon web services
Platform: Any
Classifier: Development Status :: 5 - Production/Stable
Classifier: Environment :: Console
Classifier: License :: OSI Approved :: Apache Software License
Classifier: Operating System :: OS Independent
Classifier: Programming Language :: Python
